{"chunk_definitions":[{"row":42,"row_count":1,"visible":true,"expansion_state":0,"options":{"engine":"r","label":"setup","include":false},"document_id":"0287702E","chunk_id":"csetup_chunk","chunk_label":"setup"},{"row":53,"row_count":1,"visible":true,"expansion_state":0,"options":{"engine":"r","echo":false,"label":"unnamed-chunk-1"},"document_id":"0287702E","chunk_id":"c75z5q5e3m2tk","chunk_label":"unnamed-chunk-1"},{"row":64,"row_count":1,"visible":true,"expansion_state":0,"options":{"engine":"r","echo":false,"label":"unnamed-chunk-2"},"document_id":"0287702E","chunk_id":"cer4oqu56toom","chunk_label":"unnamed-chunk-2"},{"row":77,"row_count":1,"visible":true,"expansion_state":0,"options":{"engine":"r","echo":false,"label":"unnamed-chunk-3"},"document_id":"0287702E","chunk_id":"cikhg1jp3cp33","chunk_label":"unnamed-chunk-3"},{"row":96,"row_count":1,"visible":true,"expansion_state":0,"options":{"engine":"r","echo":false,"label":"unnamed-chunk-4"},"document_id":"0287702E","chunk_id":"cbe60y2j628ai","chunk_label":"unnamed-chunk-4"},{"row":123,"row_count":1,"visible":true,"expansion_state":0,"options":{"engine":"r","echo":false,"label":"unnamed-chunk-5"},"document_id":"0287702E","chunk_id":"c98k9hsfdk6lm","chunk_label":"unnamed-chunk-5"},{"row":147,"row_count":1,"visible":true,"expansion_state":0,"options":{"engine":"r","echo":false,"label":"unnamed-chunk-6"},"document_id":"751D894A","chunk_id":"c82rkwurgfb0q","chunk_label":"unnamed-chunk-6"},{"row":165,"row_count":1,"visible":true,"expansion_state":0,"options":{"engine":"r","echo":false,"label":"unnamed-chunk-7"},"document_id":"751D894A","chunk_id":"cc57t16sdrpo9","chunk_label":"unnamed-chunk-7"},{"row":183,"row_count":1,"visible":true,"expansion_state":0,"options":{"engine":"r","echo":false,"label":"unnamed-chunk-8"},"document_id":"751D894A","chunk_id":"c9eqfpnax4mbc","chunk_label":"unnamed-chunk-8"},{"row":201,"row_count":1,"visible":true,"expansion_state":0,"options":{"engine":"r","echo":false,"label":"unnamed-chunk-9"},"document_id":"751D894A","chunk_id":"c68ybo5wl24ok","chunk_label":"unnamed-chunk-9"},{"row":219,"row_count":1,"visible":true,"expansion_state":0,"options":{"engine":"r","echo":false,"label":"unnamed-chunk-10"},"document_id":"751D894A","chunk_id":"cglhjos8u0gyt","chunk_label":"unnamed-chunk-10"},{"row":237,"row_count":1,"visible":true,"expansion_state":0,"options":{"engine":"r","echo":false,"label":"unnamed-chunk-11"},"document_id":"751D894A","chunk_id":"cjuw3ufbsmup3","chunk_label":"unnamed-chunk-11"},{"row":255,"row_count":1,"visible":true,"expansion_state":0,"options":{"engine":"r","echo":false,"label":"unnamed-chunk-12"},"document_id":"751D894A","chunk_id":"cxv59hmpt6ia3","chunk_label":"unnamed-chunk-12"},{"row":273,"row_count":1,"visible":true,"expansion_state":0,"options":{"engine":"r","echo":false,"label":"unnamed-chunk-13"},"document_id":"751D894A","chunk_id":"cbaoi8mln0nn3","chunk_label":"unnamed-chunk-13"},{"row":291,"row_count":1,"visible":true,"expansion_state":0,"options":{"engine":"r","echo":false,"label":"unnamed-chunk-14"},"document_id":"751D894A","chunk_id":"cmh68bxbi8g6n","chunk_label":"unnamed-chunk-14"},{"row":309,"row_count":1,"visible":true,"expansion_state":0,"options":{"engine":"r","echo":false,"label":"unnamed-chunk-15"},"document_id":"751D894A","chunk_id":"c0fsrkjhpsy2n","chunk_label":"unnamed-chunk-15"},{"row":314,"row_count":1,"visible":true,"expansion_state":0,"options":{"engine":"r","fig.height":8,"echo":false,"label":"unnamed-chunk-16"},"document_id":"751D894A","chunk_id":"cru6tf5nj66eq","chunk_label":"unnamed-chunk-16"},{"row":349,"row_count":1,"visible":true,"expansion_state":0,"options":{"engine":"r","warning":false,"echo":false,"label":"unnamed-chunk-17"},"document_id":"0287702E","chunk_id":"cu9ggmnb2856w","chunk_label":"unnamed-chunk-17"},{"row":353,"row_count":1,"visible":true,"expansion_state":0,"options":{},"document_id":"751D894A","chunk_id":"ci9biy181pp23","chunk_label":"unnamed-chunk-18"},{"row":362,"row_count":1,"visible":true,"expansion_state":0,"options":{"engine":"r","label":"unnamed-chunk-19"},"document_id":"751D894A","chunk_id":"cuu4pea3ymeb7","chunk_label":"unnamed-chunk-19"},{"row":381,"row_count":1,"visible":true,"expansion_state":0,"options":{"engine":"r","warning":false,"label":"unnamed-chunk-20"},"document_id":"751D894A","chunk_id":"cuaemylwqtv1k","chunk_label":"unnamed-chunk-20"},{"row":391,"row_count":1,"visible":true,"expansion_state":0,"options":{"engine":"r","fig.height":3,"warning":false,"label":"unnamed-chunk-21"},"document_id":"751D894A","chunk_id":"c7wesbp82veiv","chunk_label":"unnamed-chunk-21"},{"row":399,"row_count":1,"visible":true,"expansion_state":0,"options":{"engine":"r","label":"unnamed-chunk-22"},"document_id":"751D894A","chunk_id":"cxr65yazaio0u","chunk_label":"unnamed-chunk-22"},{"row":411,"row_count":1,"visible":true,"expansion_state":0,"options":{"engine":"r","label":"unnamed-chunk-23"},"document_id":"751D894A","chunk_id":"c65fq6yy3gh55","chunk_label":"unnamed-chunk-23"},{"row":431,"row_count":1,"visible":true,"expansion_state":0,"options":{"engine":"r","warning":false,"label":"unnamed-chunk-24"},"document_id":"751D894A","chunk_id":"cfwvy5gbfwxr7","chunk_label":"unnamed-chunk-24"},{"row":447,"row_count":1,"visible":true,"expansion_state":0,"options":{"engine":"r","warning":false,"label":"unnamed-chunk-25"},"document_id":"751D894A","chunk_id":"czt7c0c6iphj1","chunk_label":"unnamed-chunk-25"},{"row":463,"row_count":1,"visible":true,"expansion_state":0,"options":{"engine":"r","label":"unnamed-chunk-26"},"document_id":"751D894A","chunk_id":"cqmfghcjs7slb","chunk_label":"unnamed-chunk-26"},{"row":472,"row_count":1,"visible":true,"expansion_state":0,"options":{"engine":"r","label":"unnamed-chunk-27"},"document_id":"751D894A","chunk_id":"cp905w4gz7w9j","chunk_label":"unnamed-chunk-27"},{"row":483,"row_count":1,"visible":true,"expansion_state":0,"options":{"engine":"r","label":"unnamed-chunk-28"},"document_id":"751D894A","chunk_id":"ce94ishu2doi9","chunk_label":"unnamed-chunk-28"},{"row":493,"row_count":1,"visible":true,"expansion_state":0,"options":{"engine":"r","label":"unnamed-chunk-29"},"document_id":"751D894A","chunk_id":"cf409w2dmyvq8","chunk_label":"unnamed-chunk-29"},{"row":507,"row_count":1,"visible":true,"expansion_state":0,"options":{"engine":"r","label":"unnamed-chunk-30"},"document_id":"751D894A","chunk_id":"cfxl4qg9vho7o","chunk_label":"unnamed-chunk-30"},{"row":522,"row_count":1,"visible":true,"expansion_state":0,"options":{"engine":"r","label":"unnamed-chunk-31"},"document_id":"751D894A","chunk_id":"c9zjhpv3smltj","chunk_label":"unnamed-chunk-31"},{"row":536,"row_count":1,"visible":true,"expansion_state":0,"options":{"engine":"r","warning":false,"label":"unnamed-chunk-32"},"document_id":"751D894A","chunk_id":"ch453nncmg5uv","chunk_label":"unnamed-chunk-32"},{"row":565,"row_count":1,"visible":true,"expansion_state":0,"options":{"engine":"r","label":"unnamed-chunk-33"},"document_id":"751D894A","chunk_id":"c40jy890fmz3p","chunk_label":"unnamed-chunk-33"},{"row":572,"row_count":1,"visible":true,"expansion_state":0,"options":{"engine":"r","label":"unnamed-chunk-34"},"document_id":"751D894A","chunk_id":"c2wa0xjl8ghuv","chunk_label":"unnamed-chunk-34"},{"row":580,"row_count":1,"visible":true,"expansion_state":0,"options":{"engine":"r","label":"unnamed-chunk-35"},"document_id":"751D894A","chunk_id":"c0jztcl9kid8l","chunk_label":"unnamed-chunk-35"},{"row":596,"row_count":1,"visible":true,"expansion_state":0,"options":{"engine":"r","warning":false,"label":"unnamed-chunk-36"},"document_id":"751D894A","chunk_id":"cvwkesa84ysd3","chunk_label":"unnamed-chunk-36"},{"row":602,"row_count":1,"visible":true,"expansion_state":0,"options":{"engine":"r","label":"unnamed-chunk-37"},"document_id":"751D894A","chunk_id":"cqqrqvolammlp","chunk_label":"unnamed-chunk-37"},{"row":612,"row_count":1,"visible":true,"expansion_state":0,"options":{"engine":"r","label":"unnamed-chunk-38"},"document_id":"751D894A","chunk_id":"cqs5qfwcmjtbc","chunk_label":"unnamed-chunk-38"},{"row":625,"row_count":1,"visible":true,"expansion_state":0,"options":{"engine":"r","label":"unnamed-chunk-39"},"document_id":"751D894A","chunk_id":"czg0ar6e5hii9","chunk_label":"unnamed-chunk-39"},{"row":633,"row_count":1,"visible":true,"expansion_state":0,"options":{"engine":"r","label":"unnamed-chunk-40"},"document_id":"751D894A","chunk_id":"c8x7xef8t9wm3","chunk_label":"unnamed-chunk-40"},{"row":646,"row_count":1,"visible":true,"expansion_state":0,"options":{"engine":"r","label":"unnamed-chunk-41"},"document_id":"751D894A","chunk_id":"cufgn7vp8pxtd","chunk_label":"unnamed-chunk-41"},{"row":668,"row_count":1,"visible":true,"expansion_state":0,"options":{"engine":"r","label":"unnamed-chunk-60"},"document_id":"751D894A","chunk_id":"c37qcovivujp8","chunk_label":"unnamed-chunk-42"},{"row":691,"row_count":1,"visible":true,"expansion_state":0,"options":{"engine":"r","label":"unnamed-chunk-61"},"document_id":"751D894A","chunk_id":"cnnxy1y818p3j","chunk_label":"unnamed-chunk-43"},{"row":704,"row_count":1,"visible":true,"expansion_state":0,"options":{"engine":"r","label":"unnamed-chunk-82"},"document_id":"751D894A","chunk_id":"cpzwnhkcybnwf","chunk_label":"unnamed-chunk-44"},{"row":717,"row_count":1,"visible":true,"expansion_state":0,"options":{"engine":"r","label":"unnamed-chunk-81"},"document_id":"751D894A","chunk_id":"cjzeen5sqinzd","chunk_label":"unnamed-chunk-45"}],"doc_write_time":1679006635,"working_dir":null,"default_chunk_options":{}}